Django_ResaX-1.5.11.dist-info/DESCRIPTION.rst
Django_ResaX-1.5.11.dist-info/METADATA
Django_ResaX-1.5.11.dist-info/RECORD
Django_ResaX-1.5.11.dist-info/WHEEL
Django_ResaX-1.5.11.dist-info/metadata.json
Django_ResaX-1.5.11.dist-info/top_level.txt
resax/__init__.py
resax/apps.py
resax/models.py
resax/utils.py
